btc_lib-1.2.0.dist-info/licenses/LICENSE
btclib/__init__.py
btclib/address.py
btclib/bech32.py
btclib/const.py
btclib/script.py
btclib/service.py
btclib/transaction.py
btclib/utils.py
btc_lib-1.2.0.dist-info/METADATA
btc_lib-1.2.0.dist-info/WHEEL
btc_lib-1.2.0.dist-info/top_level.txt
btc_lib-1.2.0.dist-info/RECORD
