Metadata-Version: 2.4
Name: btc-lib
Version: 1.2.0
Summary: Simple Bitcoin Library
Home-page: https://github.com/qwerty-w/btc-lib
Author: qwerty-w
Author-email: qwerty-w <itsqwz@gmail.com>
License: MIT License
Project-URL: Homepage, https://github.com/qwerty-w/btc-lib
Project-URL: Repository, https://github.com/qwerty-w/btc-lib.git
Keywords: bitcoin,blockchain,library,simple,btc,lib
Requires-Python: >=3.12
License-File: LICENSE
Requires-Dist: base58check~=1.0.2
Requires-Dist: ecdsa~=0.19.0
Requires-Dist: httpx~=0.27.0
Dynamic: author
Dynamic: home-page
Dynamic: license-file
Dynamic: requires-python
